
<annotation>
	<folder>2594-n000109-Border_collie</folder>
	<filename>n134361.jpg</filename>
	<source>
		<database>THU-Dogs database</database>
	</source>
	<size>
		<width>216</width>
		<height>467</height>
		<depth>3</depth>
	</size>
	<segment>0</segment>
	<object>
	<name>Border_collie</name>
	<pose>Unspecified</pose>
	<truncated>0</truncated>
	<difficult>0</difficult>
	<headbndbox>
		<xmin>25</xmin>
		<ymin>143</ymin>
		<xmax>103</xmax>
		<ymax>237</ymax>
	</headbndbox>
	<bodybndbox>
		<xmin>21</xmin>
		<ymin>148</ymin>
		<xmax>201</xmax>
		<ymax>302</ymax>
	</bodybndbox>
</object>
</annotation>
