
<annotation>
	<folder>230-n000080-Rhodesian_ridgeback</folder>
	<filename>n122539.jpg</filename>
	<source>
		<database>THU-Dogs database</database>
	</source>
	<size>
		<width>183</width>
		<height>276</height>
		<depth>3</depth>
	</size>
	<segment>0</segment>
	<object>
	<name>Rhodesian_ridgeback</name>
	<pose>Unspecified</pose>
	<truncated>0</truncated>
	<difficult>0</difficult>
	<headbndbox>
		<xmin>52</xmin>
		<ymin>28</ymin>
		<xmax>135</xmax>
		<ymax>106</ymax>
	</headbndbox>
	<bodybndbox>
		<xmin>3</xmin>
		<ymin>22</ymin>
		<xmax>136</xmax>
		<ymax>275</ymax>
	</bodybndbox>
</object>
</annotation>
