
<annotation>
	<folder>234-n000093-Chinese_Crested_Dog</folder>
	<filename>n127934.jpg</filename>
	<source>
		<database>THU-Dogs database</database>
	</source>
	<size>
		<width>268</width>
		<height>188</height>
		<depth>3</depth>
	</size>
	<segment>0</segment>
	<object>
	<name>Chinese_Crested_Dog</name>
	<pose>Unspecified</pose>
	<truncated>0</truncated>
	<difficult>0</difficult>
	<headbndbox>
		<xmin>5</xmin>
		<ymin>2</ymin>
		<xmax>188</xmax>
		<ymax>156</ymax>
	</headbndbox>
	<bodybndbox>
		<xmin>0</xmin>
		<ymin>0</ymin>
		<xmax>186</xmax>
		<ymax>267</ymax>
	</bodybndbox>
</object>
</annotation>
