
<annotation>
	<folder>225-n000073-Great_Pyrenees</folder>
	<filename>n115217.jpg</filename>
	<source>
		<database>THU-Dogs database</database>
	</source>
	<size>
		<width>194</width>
		<height>259</height>
		<depth>3</depth>
	</size>
	<segment>0</segment>
	<object>
	<name>Great_Pyrenees</name>
	<pose>Unspecified</pose>
	<truncated>0</truncated>
	<difficult>0</difficult>
	<headbndbox>
		<xmin>79</xmin>
		<ymin>28</ymin>
		<xmax>189</xmax>
		<ymax>121</ymax>
	</headbndbox>
	<bodybndbox>
		<xmin>29</xmin>
		<ymin>21</ymin>
		<xmax>229</xmax>
		<ymax>194</ymax>
	</bodybndbox>
</object>
</annotation>
