
<annotation>
	<folder>211-n000058-Sealyham_terrier</folder>
	<filename>n118044.jpg</filename>
	<source>
		<database>THU-Dogs database</database>
	</source>
	<size>
		<width>225</width>
		<height>175</height>
		<depth>3</depth>
	</size>
	<segment>0</segment>
	<object>
	<name>Sealyham_terrier</name>
	<pose>Unspecified</pose>
	<truncated>0</truncated>
	<difficult>0</difficult>
	<headbndbox>
		<xmin>3</xmin>
		<ymin>20</ymin>
		<xmax>82</xmax>
		<ymax>96</ymax>
	</headbndbox>
	<bodybndbox>
		<xmin>3</xmin>
		<ymin>18</ymin>
		<xmax>224</xmax>
		<ymax>165</ymax>
	</bodybndbox>
</object>
</annotation>
