
<annotation>
	<folder>234-n000065-whippet</folder>
	<filename>n119169.jpg</filename>
	<source>
		<database>THU-Dogs database</database>
	</source>
	<size>
		<width>225</width>
		<height>225</height>
		<depth>3</depth>
	</size>
	<segment>0</segment>
	<object>
	<name>whippet</name>
	<pose>Unspecified</pose>
	<truncated>0</truncated>
	<difficult>0</difficult>
	<headbndbox>
		<xmin>98</xmin>
		<ymin>0</ymin>
		<xmax>177</xmax>
		<ymax>58</ymax>
	</headbndbox>
	<bodybndbox>
		<xmin>50</xmin>
		<ymin>2</ymin>
		<xmax>184</xmax>
		<ymax>222</ymax>
	</bodybndbox>
</object>
</annotation>
