
<annotation>
	<folder>7449-n000128-teddy</folder>
	<filename>n163602.jpeg</filename>
	<source>
		<database>THU-Dogs database</database>
	</source>
	<size>
		<width>720</width>
		<height>720</height>
		<depth>3</depth>
	</size>
	<segment>0</segment>
	<object>
	<name>teddy</name>
	<pose>Unspecified</pose>
	<truncated>0</truncated>
	<difficult>0</difficult>
	<headbndbox>
		<xmin>183</xmin>
		<ymin>87</ymin>
		<xmax>536</xmax>
		<ymax>462</ymax>
	</headbndbox>
	<bodybndbox>
		<xmin>131</xmin>
		<ymin>14</ymin>
		<xmax>536</xmax>
		<ymax>558</ymax>
	</bodybndbox>
</object>
</annotation>
