
<annotation>
	<folder>7449-n000128-teddy</folder>
	<filename>n163410.jpeg</filename>
	<source>
		<database>THU-Dogs database</database>
	</source>
	<size>
		<width>374</width>
		<height>500</height>
		<depth>3</depth>
	</size>
	<segment>0</segment>
	<object>
	<name>teddy</name>
	<pose>Unspecified</pose>
	<truncated>0</truncated>
	<difficult>0</difficult>
	<headbndbox>
		<xmin>74</xmin>
		<ymin>14</ymin>
		<xmax>349</xmax>
		<ymax>311</ymax>
	</headbndbox>
	<bodybndbox>
		<xmin>64</xmin>
		<ymin>14</ymin>
		<xmax>349</xmax>
		<ymax>500</ymax>
	</bodybndbox>
</object>
</annotation>
