
<annotation>
	<folder>7449-n000128-teddy</folder>
	<filename>n167208.jpeg</filename>
	<source>
		<database>THU-Dogs database</database>
	</source>
	<size>
		<width>300</width>
		<height>400</height>
		<depth>3</depth>
	</size>
	<segment>0</segment>
	<object>
	<name>teddy</name>
	<pose>Unspecified</pose>
	<truncated>0</truncated>
	<difficult>0</difficult>
	<headbndbox>
		<xmin>87</xmin>
		<ymin>85</ymin>
		<xmax>158</xmax>
		<ymax>166</ymax>
	</headbndbox>
	<bodybndbox>
		<xmin>57</xmin>
		<ymin>47</ymin>
		<xmax>275</xmax>
		<ymax>247</ymax>
	</bodybndbox>
</object>
</annotation>
