
<annotation>
	<folder>210-n000048-vizsla</folder>
	<filename>n115913.jpg</filename>
	<source>
		<database>THU-Dogs database</database>
	</source>
	<size>
		<width>266</width>
		<height>189</height>
		<depth>3</depth>
	</size>
	<segment>0</segment>
	<object>
	<name>vizsla</name>
	<pose>Unspecified</pose>
	<truncated>0</truncated>
	<difficult>0</difficult>
	<headbndbox>
		<xmin>104</xmin>
		<ymin>32</ymin>
		<xmax>189</xmax>
		<ymax>119</ymax>
	</headbndbox>
	<bodybndbox>
		<xmin>76</xmin>
		<ymin>29</ymin>
		<xmax>195</xmax>
		<ymax>186</ymax>
	</bodybndbox>
</object>
</annotation>
