
<annotation>
	<folder>216-n000063-Walker_hound</folder>
	<filename>n118842.jpg</filename>
	<source>
		<database>THU-Dogs database</database>
	</source>
	<size>
		<width>302</width>
		<height>214</height>
		<depth>3</depth>
	</size>
	<segment>0</segment>
	<object>
	<name>Walker_hound</name>
	<pose>Unspecified</pose>
	<truncated>0</truncated>
	<difficult>0</difficult>
	<headbndbox>
		<xmin>213</xmin>
		<ymin>4</ymin>
		<xmax>287</xmax>
		<ymax>73</ymax>
	</headbndbox>
	<bodybndbox>
		<xmin>0</xmin>
		<ymin>5</ymin>
		<xmax>286</xmax>
		<ymax>195</ymax>
	</bodybndbox>
</object>
</annotation>
