
<annotation>
	<folder>1160-n000003-Siberian_husky</folder>
	<filename>n102569.jpg</filename>
	<source>
		<database>THU-Dogs database</database>
	</source>
	<size>
		<width>360</width>
		<height>480</height>
		<depth>3</depth>
	</size>
	<segment>0</segment>
	<object>
	<name>Siberian_husky</name>
	<pose>Unspecified</pose>
	<truncated>0</truncated>
	<difficult>0</difficult>
	<headbndbox>
		<xmin>63</xmin>
		<ymin>49</ymin>
		<xmax>260</xmax>
		<ymax>304</ymax>
	</headbndbox>
	<bodybndbox>
		<xmin>0</xmin>
		<ymin>27</ymin>
		<xmax>329</xmax>
		<ymax>480</ymax>
	</bodybndbox>
</object>
</annotation>
