
<annotation>
	<folder>1160-n000003-Siberian_husky</folder>
	<filename>n102797.jpg</filename>
	<source>
		<database>THU-Dogs database</database>
	</source>
	<size>
		<width>270</width>
		<height>480</height>
		<depth>3</depth>
	</size>
	<segment>0</segment>
	<object>
	<name>Siberian_husky</name>
	<pose>Unspecified</pose>
	<truncated>0</truncated>
	<difficult>0</difficult>
	<headbndbox>
		<xmin>55</xmin>
		<ymin>9</ymin>
		<xmax>180</xmax>
		<ymax>182</ymax>
	</headbndbox>
	<bodybndbox>
		<xmin>55</xmin>
		<ymin>9</ymin>
		<xmax>232</xmax>
		<ymax>418</ymax>
	</bodybndbox>
</object>
</annotation>
