
<annotation>
	<folder>361-n000123-Shih_Tzu</folder>
	<filename>n154808.jpeg</filename>
	<source>
		<database>THU-Dogs database</database>
	</source>
	<size>
		<width>187</width>
		<height>406</height>
		<depth>3</depth>
	</size>
	<segment>0</segment>
	<object>
	<name>Shih_Tzu</name>
	<pose>Unspecified</pose>
	<truncated>0</truncated>
	<difficult>0</difficult>
	<headbndbox>
		<xmin>115</xmin>
		<ymin>201</ymin>
		<xmax>194</xmax>
		<ymax>279</ymax>
	</headbndbox>
	<bodybndbox>
		<xmin>0</xmin>
		<ymin>81</ymin>
		<xmax>182</xmax>
		<ymax>297</ymax>
	</bodybndbox>
</object>
</annotation>
