
<annotation>
	<folder>286-n000111-cocker_spaniel</folder>
	<filename>n136386.jpg</filename>
	<source>
		<database>THU-Dogs database</database>
	</source>
	<size>
		<width>500</width>
		<height>500</height>
		<depth>3</depth>
	</size>
	<segment>0</segment>
	<object>
	<name>cocker_spaniel</name>
	<pose>Unspecified</pose>
	<truncated>0</truncated>
	<difficult>0</difficult>
	<headbndbox>
		<xmin>34</xmin>
		<ymin>0</ymin>
		<xmax>497</xmax>
		<ymax>383</ymax>
	</headbndbox>
	<bodybndbox>
		<xmin>0</xmin>
		<ymin>0</ymin>
		<xmax>497</xmax>
		<ymax>500</ymax>
	</bodybndbox>
</object>
</annotation>
