
<annotation>
	<folder>206-n000035-Great_Dane</folder>
	<filename>n112107.jpg</filename>
	<source>
		<database>THU-Dogs database</database>
	</source>
	<size>
		<width>600</width>
		<height>450</height>
		<depth>3</depth>
	</size>
	<segment>0</segment>
	<object>
	<name>Great_Dane</name>
	<pose>Unspecified</pose>
	<truncated>0</truncated>
	<difficult>0</difficult>
	<headbndbox>
		<xmin>216</xmin>
		<ymin>82</ymin>
		<xmax>292</xmax>
		<ymax>201</ymax>
	</headbndbox>
	<bodybndbox>
		<xmin>157</xmin>
		<ymin>82</ymin>
		<xmax>330</xmax>
		<ymax>450</ymax>
	</bodybndbox>
</object>
</annotation>
