
<annotation>
	<folder>1121-n000002-French_bulldog</folder>
	<filename>n102164.jpeg</filename>
	<source>
		<database>THU-Dogs database</database>
	</source>
	<size>
		<width>418</width>
		<height>314</height>
		<depth>3</depth>
	</size>
	<segment>0</segment>
	<object>
	<name>French_bulldog</name>
	<pose>Unspecified</pose>
	<truncated>0</truncated>
	<difficult>0</difficult>
	<headbndbox>
		<xmin>241</xmin>
		<ymin>5</ymin>
		<xmax>409</xmax>
		<ymax>151</ymax>
	</headbndbox>
	<bodybndbox>
		<xmin>26</xmin>
		<ymin>5</ymin>
		<xmax>409</xmax>
		<ymax>256</ymax>
	</bodybndbox>
</object>
</annotation>
