
<annotation>
	<folder>1121-n000002-French_bulldog</folder>
	<filename>n102118.jpeg</filename>
	<source>
		<database>THU-Dogs database</database>
	</source>
	<size>
		<width>500</width>
		<height>375</height>
		<depth>3</depth>
	</size>
	<segment>0</segment>
	<object>
	<name>French_bulldog</name>
	<pose>Unspecified</pose>
	<truncated>0</truncated>
	<difficult>0</difficult>
	<headbndbox>
		<xmin>76</xmin>
		<ymin>149</ymin>
		<xmax>161</xmax>
		<ymax>285</ymax>
	</headbndbox>
	<bodybndbox>
		<xmin>76</xmin>
		<ymin>71</ymin>
		<xmax>427</xmax>
		<ymax>327</ymax>
	</bodybndbox>
</object>
</annotation>
