
<annotation>
	<folder>3083-n000117-Bichon_Frise</folder>
	<filename>n144685.jpg</filename>
	<source>
		<database>THU-Dogs database</database>
	</source>
	<size>
		<width>300</width>
		<height>400</height>
		<depth>3</depth>
	</size>
	<segment>0</segment>
	<object>
	<name>Bichon_Frise</name>
	<pose>Unspecified</pose>
	<truncated>0</truncated>
	<difficult>0</difficult>
	<headbndbox>
		<xmin>19</xmin>
		<ymin>119</ymin>
		<xmax>106</xmax>
		<ymax>220</ymax>
	</headbndbox>
	<bodybndbox>
		<xmin>16</xmin>
		<ymin>108</ymin>
		<xmax>267</xmax>
		<ymax>285</ymax>
	</bodybndbox>
</object>
</annotation>
