
<annotation>
	<folder>232-n000076-Brittany_spaniel</folder>
	<filename>n121654.jpg</filename>
	<source>
		<database>THU-Dogs database</database>
	</source>
	<size>
		<width>275</width>
		<height>183</height>
		<depth>3</depth>
	</size>
	<segment>0</segment>
	<object>
	<name>Brittany_spaniel</name>
	<pose>Unspecified</pose>
	<truncated>0</truncated>
	<difficult>0</difficult>
	<headbndbox>
		<xmin>46</xmin>
		<ymin>32</ymin>
		<xmax>115</xmax>
		<ymax>98</ymax>
	</headbndbox>
	<bodybndbox>
		<xmin>48</xmin>
		<ymin>16</ymin>
		<xmax>244</xmax>
		<ymax>166</ymax>
	</bodybndbox>
</object>
</annotation>
