
<annotation>
	<folder>1043-n000001-Shiba_Dog</folder>
	<filename>n100242.jpg</filename>
	<source>
		<database>THU-Dogs database</database>
	</source>
	<size>
		<width>403</width>
		<height>302</height>
		<depth>3</depth>
	</size>
	<segment>0</segment>
	<object>
	<name>Shiba_Dog</name>
	<pose>Unspecified</pose>
	<truncated>0</truncated>
	<difficult>0</difficult>
	<headbndbox>
		<xmin>64</xmin>
		<ymin>98</ymin>
		<xmax>175</xmax>
		<ymax>201</ymax>
	</headbndbox>
	<bodybndbox>
		<xmin>50</xmin>
		<ymin>75</ymin>
		<xmax>328</xmax>
		<ymax>213</ymax>
	</bodybndbox>
</object>
</annotation>
