
<annotation>
	<folder>340-n000120-Yorkshire_terrier</folder>
	<filename>n150844.jpeg</filename>
	<source>
		<database>THU-Dogs database</database>
	</source>
	<size>
		<width>403</width>
		<height>302</height>
		<depth>3</depth>
	</size>
	<segment>0</segment>
	<object>
	<name>Yorkshire_terrier</name>
	<pose>Unspecified</pose>
	<truncated>0</truncated>
	<difficult>0</difficult>
	<headbndbox>
		<xmin>194</xmin>
		<ymin>52</ymin>
		<xmax>319</xmax>
		<ymax>184</ymax>
	</headbndbox>
	<bodybndbox>
		<xmin>51</xmin>
		<ymin>23</ymin>
		<xmax>322</xmax>
		<ymax>296</ymax>
	</bodybndbox>
</object>
</annotation>
