
<annotation>
	<folder>340-n000120-Yorkshire_terrier</folder>
	<filename>n150731.jpeg</filename>
	<source>
		<database>THU-Dogs database</database>
	</source>
	<size>
		<width>376</width>
		<height>667</height>
		<depth>3</depth>
	</size>
	<segment>0</segment>
	<object>
	<name>Yorkshire_terrier</name>
	<pose>Unspecified</pose>
	<truncated>0</truncated>
	<difficult>0</difficult>
	<headbndbox>
		<xmin>76</xmin>
		<ymin>69</ymin>
		<xmax>291</xmax>
		<ymax>297</ymax>
	</headbndbox>
	<bodybndbox>
		<xmin>70</xmin>
		<ymin>63</ymin>
		<xmax>339</xmax>
		<ymax>494</ymax>
	</bodybndbox>
</object>
</annotation>
