
<annotation>
	<folder>217-n000046-Norwegian_elkhound</folder>
	<filename>n115852.jpg</filename>
	<source>
		<database>THU-Dogs database</database>
	</source>
	<size>
		<width>225</width>
		<height>225</height>
		<depth>3</depth>
	</size>
	<segment>0</segment>
	<object>
	<name>Norwegian_elkhound</name>
	<pose>Unspecified</pose>
	<truncated>0</truncated>
	<difficult>0</difficult>
	<headbndbox>
		<xmin>134</xmin>
		<ymin>19</ymin>
		<xmax>197</xmax>
		<ymax>109</ymax>
	</headbndbox>
	<bodybndbox>
		<xmin>15</xmin>
		<ymin>17</ymin>
		<xmax>205</xmax>
		<ymax>214</ymax>
	</bodybndbox>
</object>
</annotation>
