
<annotation>
	<folder>3580-n000122-Labrador_retriever</folder>
	<filename>n152113.jpg</filename>
	<source>
		<database>THU-Dogs database</database>
	</source>
	<size>
		<width>480</width>
		<height>360</height>
		<depth>3</depth>
	</size>
	<segment>0</segment>
	<object>
	<name>Labrador_retriever</name>
	<pose>Unspecified</pose>
	<truncated>0</truncated>
	<difficult>0</difficult>
	<headbndbox>
		<xmin>247</xmin>
		<ymin>67</ymin>
		<xmax>362</xmax>
		<ymax>170</ymax>
	</headbndbox>
	<bodybndbox>
		<xmin>36</xmin>
		<ymin>55</ymin>
		<xmax>369</xmax>
		<ymax>349</ymax>
	</bodybndbox>
</object>
</annotation>
