
<annotation>
	<folder>3580-n000122-Labrador_retriever</folder>
	<filename>n152854.jpeg</filename>
	<source>
		<database>THU-Dogs database</database>
	</source>
	<size>
		<width>750</width>
		<height>750</height>
		<depth>3</depth>
	</size>
	<segment>0</segment>
	<object>
	<name>Labrador_retriever</name>
	<pose>Unspecified</pose>
	<truncated>0</truncated>
	<difficult>0</difficult>
	<headbndbox>
		<xmin>49</xmin>
		<ymin>0</ymin>
		<xmax>731</xmax>
		<ymax>726</ymax>
	</headbndbox>
	<bodybndbox>
		<xmin>42</xmin>
		<ymin>0</ymin>
		<xmax>742</xmax>
		<ymax>750</ymax>
	</bodybndbox>
</object>
</annotation>
