
<annotation>
	<folder>3580-n000122-Labrador_retriever</folder>
	<filename>n153445.jpeg</filename>
	<source>
		<database>THU-Dogs database</database>
	</source>
	<size>
		<width>216</width>
		<height>468</height>
		<depth>3</depth>
	</size>
	<segment>0</segment>
	<object>
	<name>Labrador_retriever</name>
	<pose>Unspecified</pose>
	<truncated>0</truncated>
	<difficult>0</difficult>
	<headbndbox>
		<xmin>6</xmin>
		<ymin>77</ymin>
		<xmax>154</xmax>
		<ymax>227</ymax>
	</headbndbox>
	<bodybndbox>
		<xmin>0</xmin>
		<ymin>55</ymin>
		<xmax>216</xmax>
		<ymax>417</ymax>
	</bodybndbox>
</object>
</annotation>
