
<annotation>
	<folder>3580-n000122-Labrador_retriever</folder>
	<filename>n153710.jpeg</filename>
	<source>
		<database>THU-Dogs database</database>
	</source>
	<size>
		<width>312</width>
		<height>416</height>
		<depth>3</depth>
	</size>
	<segment>0</segment>
	<object>
	<name>Labrador_retriever</name>
	<pose>Unspecified</pose>
	<truncated>0</truncated>
	<difficult>0</difficult>
	<headbndbox>
		<xmin>79</xmin>
		<ymin>125</ymin>
		<xmax>177</xmax>
		<ymax>215</ymax>
	</headbndbox>
	<bodybndbox>
		<xmin>33</xmin>
		<ymin>114</ymin>
		<xmax>205</xmax>
		<ymax>379</ymax>
	</bodybndbox>
</object>
</annotation>
