
<annotation>
	<folder>3580-n000122-Labrador_retriever</folder>
	<filename>n153772.jpeg</filename>
	<source>
		<database>THU-Dogs database</database>
	</source>
	<size>
		<width>251</width>
		<height>447</height>
		<depth>3</depth>
	</size>
	<segment>0</segment>
	<object>
	<name>Labrador_retriever</name>
	<pose>Unspecified</pose>
	<truncated>0</truncated>
	<difficult>0</difficult>
	<headbndbox>
		<xmin>39</xmin>
		<ymin>53</ymin>
		<xmax>181</xmax>
		<ymax>196</ymax>
	</headbndbox>
	<bodybndbox>
		<xmin>15</xmin>
		<ymin>36</ymin>
		<xmax>206</xmax>
		<ymax>437</ymax>
	</bodybndbox>
</object>
</annotation>
