
<annotation>
	<folder>207-n000011-Irish_setter</folder>
	<filename>n107674.jpg</filename>
	<source>
		<database>THU-Dogs database</database>
	</source>
	<size>
		<width>311</width>
		<height>162</height>
		<depth>3</depth>
	</size>
	<segment>0</segment>
	<object>
	<name>Irish_setter</name>
	<pose>Unspecified</pose>
	<truncated>0</truncated>
	<difficult>0</difficult>
	<headbndbox>
		<xmin>208</xmin>
		<ymin>8</ymin>
		<xmax>268</xmax>
		<ymax>62</ymax>
	</headbndbox>
	<bodybndbox>
		<xmin>16</xmin>
		<ymin>10</ymin>
		<xmax>270</xmax>
		<ymax>162</ymax>
	</bodybndbox>
</object>
</annotation>
