
<annotation>
	<folder>207-n000044-bloodhound</folder>
	<filename>n115324.jpg</filename>
	<source>
		<database>THU-Dogs database</database>
	</source>
	<size>
		<width>375</width>
		<height>500</height>
		<depth>3</depth>
	</size>
	<segment>0</segment>
	<object>
	<name>bloodhound</name>
	<pose>Unspecified</pose>
	<truncated>0</truncated>
	<difficult>0</difficult>
	<headbndbox>
		<xmin>109</xmin>
		<ymin>88</ymin>
		<xmax>254</xmax>
		<ymax>249</ymax>
	</headbndbox>
	<bodybndbox>
		<xmin>44</xmin>
		<ymin>88</ymin>
		<xmax>356</xmax>
		<ymax>426</ymax>
	</bodybndbox>
</object>
</annotation>
