
<annotation>
	<folder>2925-n000114-toy_poodle</folder>
	<filename>n141678.jpg</filename>
	<source>
		<database>THU-Dogs database</database>
	</source>
	<size>
		<width>320</width>
		<height>426</height>
		<depth>3</depth>
	</size>
	<segment>0</segment>
	<object>
	<name>toy_poodle</name>
	<pose>Unspecified</pose>
	<truncated>0</truncated>
	<difficult>0</difficult>
	<headbndbox>
		<xmin>60</xmin>
		<ymin>50</ymin>
		<xmax>260</xmax>
		<ymax>291</ymax>
	</headbndbox>
	<bodybndbox>
		<xmin>29</xmin>
		<ymin>0</ymin>
		<xmax>260</xmax>
		<ymax>375</ymax>
	</bodybndbox>
</object>
</annotation>
