
<annotation>
	<folder>2925-n000114-toy_poodle</folder>
	<filename>n142963.jpeg</filename>
	<source>
		<database>THU-Dogs database</database>
	</source>
	<size>
		<width>193</width>
		<height>418</height>
		<depth>3</depth>
	</size>
	<segment>0</segment>
	<object>
	<name>toy_poodle</name>
	<pose>Unspecified</pose>
	<truncated>0</truncated>
	<difficult>0</difficult>
	<headbndbox>
		<xmin>0</xmin>
		<ymin>125</ymin>
		<xmax>84</xmax>
		<ymax>237</ymax>
	</headbndbox>
	<bodybndbox>
		<xmin>0</xmin>
		<ymin>125</ymin>
		<xmax>193</xmax>
		<ymax>325</ymax>
	</bodybndbox>
</object>
</annotation>
