
<annotation>
	<folder>798-n000130-pug</folder>
	<filename>n169171.jpg</filename>
	<source>
		<database>THU-Dogs database</database>
	</source>
	<size>
		<width>500</width>
		<height>326</height>
		<depth>3</depth>
	</size>
	<segment>0</segment>
	<object>
	<name>pug</name>
	<pose>Unspecified</pose>
	<truncated>0</truncated>
	<difficult>0</difficult>
	<headbndbox>
		<xmin>305</xmin>
		<ymin>100</ymin>
		<xmax>434</xmax>
		<ymax>198</ymax>
	</headbndbox>
	<bodybndbox>
		<xmin>295</xmin>
		<ymin>89</ymin>
		<xmax>436</xmax>
		<ymax>257</ymax>
	</bodybndbox>
</object>
</annotation>
