
<annotation>
	<folder>798-n000130-pug</folder>
	<filename>n169840.jpeg</filename>
	<source>
		<database>THU-Dogs database</database>
	</source>
	<size>
		<width>301</width>
		<height>402</height>
		<depth>3</depth>
	</size>
	<segment>0</segment>
	<object>
	<name>pug</name>
	<pose>Unspecified</pose>
	<truncated>0</truncated>
	<difficult>0</difficult>
	<headbndbox>
		<xmin>8</xmin>
		<ymin>57</ymin>
		<xmax>275</xmax>
		<ymax>281</ymax>
	</headbndbox>
	<bodybndbox>
		<xmin>0</xmin>
		<ymin>37</ymin>
		<xmax>287</xmax>
		<ymax>355</ymax>
	</bodybndbox>
</object>
</annotation>
