
<annotation>
	<folder>215-n000031-Newfoundland</folder>
	<filename>n111921.jpg</filename>
	<source>
		<database>THU-Dogs database</database>
	</source>
	<size>
		<width>500</width>
		<height>394</height>
		<depth>3</depth>
	</size>
	<segment>0</segment>
	<object>
	<name>Newfoundland</name>
	<pose>Unspecified</pose>
	<truncated>0</truncated>
	<difficult>0</difficult>
	<headbndbox>
		<xmin>133</xmin>
		<ymin>9</ymin>
		<xmax>333</xmax>
		<ymax>185</ymax>
	</headbndbox>
	<bodybndbox>
		<xmin>2</xmin>
		<ymin>2</ymin>
		<xmax>385</xmax>
		<ymax>394</ymax>
	</bodybndbox>
</object>
</annotation>
