
<annotation>
	<folder>217-n000014-otterhound</folder>
	<filename>n108496.jpg</filename>
	<source>
		<database>THU-Dogs database</database>
	</source>
	<size>
		<width>183</width>
		<height>275</height>
		<depth>3</depth>
	</size>
	<segment>0</segment>
	<object>
	<name>otterhound</name>
	<pose>Unspecified</pose>
	<truncated>0</truncated>
	<difficult>0</difficult>
	<headbndbox>
		<xmin>69</xmin>
		<ymin>27</ymin>
		<xmax>147</xmax>
		<ymax>115</ymax>
	</headbndbox>
	<bodybndbox>
		<xmin>43</xmin>
		<ymin>22</ymin>
		<xmax>160</xmax>
		<ymax>262</ymax>
	</bodybndbox>
</object>
</annotation>
