
<annotation>
	<folder>217-n000014-otterhound</folder>
	<filename>n108527.jpg</filename>
	<source>
		<database>THU-Dogs database</database>
	</source>
	<size>
		<width>300</width>
		<height>168</height>
		<depth>3</depth>
	</size>
	<segment>0</segment>
	<object>
	<name>otterhound</name>
	<pose>Unspecified</pose>
	<truncated>0</truncated>
	<difficult>0</difficult>
	<headbndbox>
		<xmin>147</xmin>
		<ymin>5</ymin>
		<xmax>252</xmax>
		<ymax>110</ymax>
	</headbndbox>
	<bodybndbox>
		<xmin>124</xmin>
		<ymin>5</ymin>
		<xmax>251</xmax>
		<ymax>168</ymax>
	</bodybndbox>
</object>
</annotation>
