
<annotation>
	<folder>3336-n000121-chinese_rural_dog</folder>
	<filename>n147481.jpeg</filename>
	<source>
		<database>THU-Dogs database</database>
	</source>
	<size>
		<width>330</width>
		<height>440</height>
		<depth>3</depth>
	</size>
	<segment>0</segment>
	<object>
	<name>chinese_rural_dog</name>
	<pose>Unspecified</pose>
	<truncated>0</truncated>
	<difficult>0</difficult>
	<headbndbox>
		<xmin>119</xmin>
		<ymin>134</ymin>
		<xmax>227</xmax>
		<ymax>239</ymax>
	</headbndbox>
	<bodybndbox>
		<xmin>119</xmin>
		<ymin>134</ymin>
		<xmax>303</xmax>
		<ymax>320</ymax>
	</bodybndbox>
</object>
</annotation>
