
<annotation>
	<folder>3336-n000121-chinese_rural_dog</folder>
	<filename>n148218.jpeg</filename>
	<source>
		<database>THU-Dogs database</database>
	</source>
	<size>
		<width>180</width>
		<height>400</height>
		<depth>3</depth>
	</size>
	<segment>0</segment>
	<object>
	<name>chinese_rural_dog</name>
	<pose>Unspecified</pose>
	<truncated>0</truncated>
	<difficult>0</difficult>
	<headbndbox>
		<xmin>119</xmin>
		<ymin>140</ymin>
		<xmax>180</xmax>
		<ymax>218</ymax>
	</headbndbox>
	<bodybndbox>
		<xmin>0</xmin>
		<ymin>140</ymin>
		<xmax>180</xmax>
		<ymax>276</ymax>
	</bodybndbox>
</object>
</annotation>
