
<annotation>
	<folder>2909-n000116-Cardigan</folder>
	<filename>n137267.jpg</filename>
	<source>
		<database>THU-Dogs database</database>
	</source>
	<size>
		<width>500</width>
		<height>323</height>
		<depth>3</depth>
	</size>
	<segment>0</segment>
	<object>
	<name>Cardigan</name>
	<pose>Unspecified</pose>
	<truncated>0</truncated>
	<difficult>0</difficult>
	<headbndbox>
		<xmin>60</xmin>
		<ymin>2</ymin>
		<xmax>312</xmax>
		<ymax>302</ymax>
	</headbndbox>
	<bodybndbox>
		<xmin>61</xmin>
		<ymin>0</ymin>
		<xmax>376</xmax>
		<ymax>320</ymax>
	</bodybndbox>
</object>
</annotation>
