
<annotation>
	<folder>2909-n000116-Cardigan</folder>
	<filename>n137302.jpg</filename>
	<source>
		<database>THU-Dogs database</database>
	</source>
	<size>
		<width>500</width>
		<height>334</height>
		<depth>3</depth>
	</size>
	<segment>0</segment>
	<object>
	<name>Cardigan</name>
	<pose>Unspecified</pose>
	<truncated>0</truncated>
	<difficult>0</difficult>
	<headbndbox>
		<xmin>254</xmin>
		<ymin>118</ymin>
		<xmax>318</xmax>
		<ymax>208</ymax>
	</headbndbox>
	<bodybndbox>
		<xmin>165</xmin>
		<ymin>119</ymin>
		<xmax>329</xmax>
		<ymax>272</ymax>
	</bodybndbox>
</object>
</annotation>
