
<annotation>
	<folder>2909-n000116-Cardigan</folder>
	<filename>n138960.jpeg</filename>
	<source>
		<database>THU-Dogs database</database>
	</source>
	<size>
		<width>408</width>
		<height>408</height>
		<depth>3</depth>
	</size>
	<segment>0</segment>
	<object>
	<name>Cardigan</name>
	<pose>Unspecified</pose>
	<truncated>0</truncated>
	<difficult>0</difficult>
	<headbndbox>
		<xmin>126</xmin>
		<ymin>133</ymin>
		<xmax>281</xmax>
		<ymax>289</ymax>
	</headbndbox>
	<bodybndbox>
		<xmin>64</xmin>
		<ymin>129</ymin>
		<xmax>329</xmax>
		<ymax>408</ymax>
	</bodybndbox>
</object>
</annotation>
