
<annotation>
	<folder>2909-n000116-Cardigan</folder>
	<filename>n139728.jpeg</filename>
	<source>
		<database>THU-Dogs database</database>
	</source>
	<size>
		<width>374</width>
		<height>500</height>
		<depth>3</depth>
	</size>
	<segment>0</segment>
	<object>
	<name>Cardigan</name>
	<pose>Unspecified</pose>
	<truncated>0</truncated>
	<difficult>0</difficult>
	<headbndbox>
		<xmin>58</xmin>
		<ymin>64</ymin>
		<xmax>250</xmax>
		<ymax>292</ymax>
	</headbndbox>
	<bodybndbox>
		<xmin>50</xmin>
		<ymin>59</ymin>
		<xmax>277</xmax>
		<ymax>400</ymax>
	</bodybndbox>
</object>
</annotation>
