
<annotation>
	<folder>2909-n000116-Cardigan</folder>
	<filename>n139955.jpeg</filename>
	<source>
		<database>THU-Dogs database</database>
	</source>
	<size>
		<width>418</width>
		<height>314</height>
		<depth>3</depth>
	</size>
	<segment>0</segment>
	<object>
	<name>Cardigan</name>
	<pose>Unspecified</pose>
	<truncated>0</truncated>
	<difficult>0</difficult>
	<headbndbox>
		<xmin>60</xmin>
		<ymin>0</ymin>
		<xmax>195</xmax>
		<ymax>104</ymax>
	</headbndbox>
	<bodybndbox>
		<xmin>50</xmin>
		<ymin>0</ymin>
		<xmax>326</xmax>
		<ymax>292</ymax>
	</bodybndbox>
</object>
</annotation>
