
<annotation>
	<folder>2342-n000102-miniature_schnauzer</folder>
	<filename>n130179.jpg</filename>
	<source>
		<database>THU-Dogs database</database>
	</source>
	<size>
		<width>540</width>
		<height>540</height>
		<depth>3</depth>
	</size>
	<segment>0</segment>
	<object>
	<name>miniature_schnauzer</name>
	<pose>Unspecified</pose>
	<truncated>0</truncated>
	<difficult>0</difficult>
	<headbndbox>
		<xmin>300</xmin>
		<ymin>101</ymin>
		<xmax>470</xmax>
		<ymax>292</ymax>
	</headbndbox>
	<bodybndbox>
		<xmin>40</xmin>
		<ymin>90</ymin>
		<xmax>482</xmax>
		<ymax>447</ymax>
	</bodybndbox>
</object>
</annotation>
