
<annotation>
	<folder>2342-n000102-miniature_schnauzer</folder>
	<filename>n130420.jpeg</filename>
	<source>
		<database>THU-Dogs database</database>
	</source>
	<size>
		<width>310</width>
		<height>466</height>
		<depth>3</depth>
	</size>
	<segment>0</segment>
	<object>
	<name>miniature_schnauzer</name>
	<pose>Unspecified</pose>
	<truncated>0</truncated>
	<difficult>0</difficult>
	<headbndbox>
		<xmin>94</xmin>
		<ymin>61</ymin>
		<xmax>222</xmax>
		<ymax>180</ymax>
	</headbndbox>
	<bodybndbox>
		<xmin>81</xmin>
		<ymin>56</ymin>
		<xmax>250</xmax>
		<ymax>372</ymax>
	</bodybndbox>
</object>
</annotation>
