
<annotation>
	<folder>420-n000124-Chihuahua</folder>
	<filename>n154927.jpg</filename>
	<source>
		<database>THU-Dogs database</database>
	</source>
	<size>
		<width>500</width>
		<height>375</height>
		<depth>3</depth>
	</size>
	<segment>0</segment>
	<object>
	<name>Chihuahua</name>
	<pose>Unspecified</pose>
	<truncated>0</truncated>
	<difficult>0</difficult>
	<headbndbox>
		<xmin>307</xmin>
		<ymin>142</ymin>
		<xmax>469</xmax>
		<ymax>301</ymax>
	</headbndbox>
	<bodybndbox>
		<xmin>147</xmin>
		<ymin>93</ymin>
		<xmax>471</xmax>
		<ymax>302</ymax>
	</bodybndbox>
</object>
</annotation>
