
<annotation>
	<folder>200-n000010-miniature_poodle</folder>
	<filename>n107510.jpg</filename>
	<source>
		<database>THU-Dogs database</database>
	</source>
	<size>
		<width>800</width>
		<height>533</height>
		<depth>3</depth>
	</size>
	<segment>0</segment>
	<object>
	<name>miniature_poodle</name>
	<pose>Unspecified</pose>
	<truncated>0</truncated>
	<difficult>0</difficult>
	<headbndbox>
		<xmin>186</xmin>
		<ymin>31</ymin>
		<xmax>455</xmax>
		<ymax>310</ymax>
	</headbndbox>
	<bodybndbox>
		<xmin>196</xmin>
		<ymin>31</ymin>
		<xmax>692</xmax>
		<ymax>519</ymax>
	</bodybndbox>
</object>
</annotation>
