
<annotation>
	<folder>274-n000110-Shetland_sheepdog</folder>
	<filename>n136337.jpeg</filename>
	<source>
		<database>THU-Dogs database</database>
	</source>
	<size>
		<width>374</width>
		<height>500</height>
		<depth>3</depth>
	</size>
	<segment>0</segment>
	<object>
	<name>Shetland_sheepdog</name>
	<pose>Unspecified</pose>
	<truncated>0</truncated>
	<difficult>0</difficult>
	<headbndbox>
		<xmin>103</xmin>
		<ymin>83</ymin>
		<xmax>287</xmax>
		<ymax>284</ymax>
	</headbndbox>
	<bodybndbox>
		<xmin>70</xmin>
		<ymin>83</ymin>
		<xmax>329</xmax>
		<ymax>495</ymax>
	</bodybndbox>
</object>
</annotation>
