
<annotation>
	<folder>200-n000008-Airedale</folder>
	<filename>n107088.jpg</filename>
	<source>
		<database>THU-Dogs database</database>
	</source>
	<size>
		<width>500</width>
		<height>317</height>
		<depth>3</depth>
	</size>
	<segment>0</segment>
	<object>
	<name>Airedale</name>
	<pose>Unspecified</pose>
	<truncated>0</truncated>
	<difficult>0</difficult>
	<headbndbox>
		<xmin>169</xmin>
		<ymin>47</ymin>
		<xmax>336</xmax>
		<ymax>215</ymax>
	</headbndbox>
	<bodybndbox>
		<xmin>129</xmin>
		<ymin>47</ymin>
		<xmax>435</xmax>
		<ymax>317</ymax>
	</bodybndbox>
</object>
</annotation>
