
<annotation>
	<folder>2192-n000088-Samoyed</folder>
	<filename>n124358.jpg</filename>
	<source>
		<database>THU-Dogs database</database>
	</source>
	<size>
		<width>540</width>
		<height>540</height>
		<depth>3</depth>
	</size>
	<segment>0</segment>
	<object>
	<name>Samoyed</name>
	<pose>Unspecified</pose>
	<truncated>0</truncated>
	<difficult>0</difficult>
	<headbndbox>
		<xmin>175</xmin>
		<ymin>41</ymin>
		<xmax>364</xmax>
		<ymax>267</ymax>
	</headbndbox>
	<bodybndbox>
		<xmin>175</xmin>
		<ymin>20</ymin>
		<xmax>446</xmax>
		<ymax>447</ymax>
	</bodybndbox>
</object>
</annotation>
