
<annotation>
	<folder>2192-n000088-Samoyed</folder>
	<filename>n124275.jpg</filename>
	<source>
		<database>THU-Dogs database</database>
	</source>
	<size>
		<width>314</width>
		<height>418</height>
		<depth>3</depth>
	</size>
	<segment>0</segment>
	<object>
	<name>Samoyed</name>
	<pose>Unspecified</pose>
	<truncated>0</truncated>
	<difficult>0</difficult>
	<headbndbox>
		<xmin>52</xmin>
		<ymin>3</ymin>
		<xmax>289</xmax>
		<ymax>218</ymax>
	</headbndbox>
	<bodybndbox>
		<xmin>26</xmin>
		<ymin>0</ymin>
		<xmax>314</xmax>
		<ymax>418</ymax>
	</bodybndbox>
</object>
</annotation>
