
<annotation>
	<folder>2192-n000088-Samoyed</folder>
	<filename>n125869.jpeg</filename>
	<source>
		<database>THU-Dogs database</database>
	</source>
	<size>
		<width>480</width>
		<height>234</height>
		<depth>3</depth>
	</size>
	<segment>0</segment>
	<object>
	<name>Samoyed</name>
	<pose>Unspecified</pose>
	<truncated>0</truncated>
	<difficult>0</difficult>
	<headbndbox>
		<xmin>334</xmin>
		<ymin>4</ymin>
		<xmax>467</xmax>
		<ymax>113</ymax>
	</headbndbox>
	<bodybndbox>
		<xmin>100</xmin>
		<ymin>0</ymin>
		<xmax>466</xmax>
		<ymax>230</ymax>
	</bodybndbox>
</object>
</annotation>
