
<annotation>
	<folder>2192-n000088-Samoyed</folder>
	<filename>n126020.jpeg</filename>
	<source>
		<database>THU-Dogs database</database>
	</source>
	<size>
		<width>416</width>
		<height>312</height>
		<depth>3</depth>
	</size>
	<segment>0</segment>
	<object>
	<name>Samoyed</name>
	<pose>Unspecified</pose>
	<truncated>0</truncated>
	<difficult>0</difficult>
	<headbndbox>
		<xmin>5</xmin>
		<ymin>21</ymin>
		<xmax>104</xmax>
		<ymax>142</ymax>
	</headbndbox>
	<bodybndbox>
		<xmin>0</xmin>
		<ymin>12</ymin>
		<xmax>357</xmax>
		<ymax>310</ymax>
	</bodybndbox>
</object>
</annotation>
