
<annotation>
	<folder>225-n000082-boxer</folder>
	<filename>n122987.jpg</filename>
	<source>
		<database>THU-Dogs database</database>
	</source>
	<size>
		<width>299</width>
		<height>168</height>
		<depth>3</depth>
	</size>
	<segment>0</segment>
	<object>
	<name>boxer</name>
	<pose>Unspecified</pose>
	<truncated>0</truncated>
	<difficult>0</difficult>
	<headbndbox>
		<xmin>132</xmin>
		<ymin>0</ymin>
		<xmax>203</xmax>
		<ymax>65</ymax>
	</headbndbox>
	<bodybndbox>
		<xmin>12</xmin>
		<ymin>0</ymin>
		<xmax>217</xmax>
		<ymax>168</ymax>
	</bodybndbox>
</object>
</annotation>
