
<annotation>
	<folder>1936-n000005-Pomeranian</folder>
	<filename>n105908.jpg</filename>
	<source>
		<database>THU-Dogs database</database>
	</source>
	<size>
		<width>400</width>
		<height>300</height>
		<depth>3</depth>
	</size>
	<segment>0</segment>
	<object>
	<name>Pomeranian</name>
	<pose>Unspecified</pose>
	<truncated>0</truncated>
	<difficult>0</difficult>
	<headbndbox>
		<xmin>62</xmin>
		<ymin>50</ymin>
		<xmax>177</xmax>
		<ymax>141</ymax>
	</headbndbox>
	<bodybndbox>
		<xmin>57</xmin>
		<ymin>44</ymin>
		<xmax>364</xmax>
		<ymax>247</ymax>
	</bodybndbox>
</object>
</annotation>
