
<annotation>
	<folder>1936-n000005-Pomeranian</folder>
	<filename>n105711.jpeg</filename>
	<source>
		<database>THU-Dogs database</database>
	</source>
	<size>
		<width>414</width>
		<height>736</height>
		<depth>3</depth>
	</size>
	<segment>0</segment>
	<object>
	<name>Pomeranian</name>
	<pose>Unspecified</pose>
	<truncated>0</truncated>
	<difficult>0</difficult>
	<headbndbox>
		<xmin>182</xmin>
		<ymin>195</ymin>
		<xmax>376</xmax>
		<ymax>339</ymax>
	</headbndbox>
	<bodybndbox>
		<xmin>0</xmin>
		<ymin>187</ymin>
		<xmax>386</xmax>
		<ymax>447</ymax>
	</bodybndbox>
</object>
</annotation>
