
<annotation>
	<folder>245-n000098-Australian_Shepherd</folder>
	<filename>n128943.jpg</filename>
	<source>
		<database>THU-Dogs database</database>
	</source>
	<size>
		<width>800</width>
		<height>754</height>
		<depth>3</depth>
	</size>
	<segment>0</segment>
	<object>
	<name>Australian_Shepherd</name>
	<pose>Unspecified</pose>
	<truncated>0</truncated>
	<difficult>0</difficult>
	<headbndbox>
		<xmin>282</xmin>
		<ymin>89</ymin>
		<xmax>516</xmax>
		<ymax>304</ymax>
	</headbndbox>
	<bodybndbox>
		<xmin>229</xmin>
		<ymin>81</ymin>
		<xmax>567</xmax>
		<ymax>713</ymax>
	</bodybndbox>
</object>
</annotation>
