
<annotation>
	<folder>257-n000108-Old_English_sheepdog</folder>
	<filename>n133379.jpg</filename>
	<source>
		<database>THU-Dogs database</database>
	</source>
	<size>
		<width>375</width>
		<height>500</height>
		<depth>3</depth>
	</size>
	<segment>0</segment>
	<object>
	<name>Old_English_sheepdog</name>
	<pose>Unspecified</pose>
	<truncated>0</truncated>
	<difficult>0</difficult>
	<headbndbox>
		<xmin>26</xmin>
		<ymin>44</ymin>
		<xmax>220</xmax>
		<ymax>256</ymax>
	</headbndbox>
	<bodybndbox>
		<xmin>0</xmin>
		<ymin>44</ymin>
		<xmax>367</xmax>
		<ymax>500</ymax>
	</bodybndbox>
</object>
</annotation>
