
<annotation>
	<folder>257-n000108-Old_English_sheepdog</folder>
	<filename>n133259.jpg</filename>
	<source>
		<database>THU-Dogs database</database>
	</source>
	<size>
		<width>500</width>
		<height>419</height>
		<depth>3</depth>
	</size>
	<segment>0</segment>
	<object>
	<name>Old_English_sheepdog</name>
	<pose>Unspecified</pose>
	<truncated>0</truncated>
	<difficult>0</difficult>
	<headbndbox>
		<xmin>75</xmin>
		<ymin>65</ymin>
		<xmax>416</xmax>
		<ymax>378</ymax>
	</headbndbox>
	<bodybndbox>
		<xmin>47</xmin>
		<ymin>65</ymin>
		<xmax>440</xmax>
		<ymax>378</ymax>
	</bodybndbox>
</object>
</annotation>
