
<annotation>
	<folder>211-n000052-Dandie_Dinmont</folder>
	<filename>n116737.jpg</filename>
	<source>
		<database>THU-Dogs database</database>
	</source>
	<size>
		<width>275</width>
		<height>183</height>
		<depth>3</depth>
	</size>
	<segment>0</segment>
	<object>
	<name>Dandie_Dinmont</name>
	<pose>Unspecified</pose>
	<truncated>0</truncated>
	<difficult>0</difficult>
	<headbndbox>
		<xmin>32</xmin>
		<ymin>32</ymin>
		<xmax>100</xmax>
		<ymax>104</ymax>
	</headbndbox>
	<bodybndbox>
		<xmin>28</xmin>
		<ymin>29</ymin>
		<xmax>263</xmax>
		<ymax>163</ymax>
	</bodybndbox>
</object>
</annotation>
