
<annotation>
	<folder>5355-n000126-golden_retriever</folder>
	<filename>n156679.jpeg</filename>
	<source>
		<database>THU-Dogs database</database>
	</source>
	<size>
		<width>414</width>
		<height>736</height>
		<depth>3</depth>
	</size>
	<segment>0</segment>
	<object>
	<name>golden_retriever</name>
	<pose>Unspecified</pose>
	<truncated>0</truncated>
	<difficult>0</difficult>
	<headbndbox>
		<xmin>70</xmin>
		<ymin>169</ymin>
		<xmax>321</xmax>
		<ymax>438</ymax>
	</headbndbox>
	<bodybndbox>
		<xmin>44</xmin>
		<ymin>171</ymin>
		<xmax>327</xmax>
		<ymax>641</ymax>
	</bodybndbox>
</object>
</annotation>
