
<annotation>
	<folder>5355-n000126-golden_retriever</folder>
	<filename>n156729.jpeg</filename>
	<source>
		<database>THU-Dogs database</database>
	</source>
	<size>
		<width>432</width>
		<height>432</height>
		<depth>3</depth>
	</size>
	<segment>0</segment>
	<object>
	<name>golden_retriever</name>
	<pose>Unspecified</pose>
	<truncated>0</truncated>
	<difficult>0</difficult>
	<headbndbox>
		<xmin>72</xmin>
		<ymin>102</ymin>
		<xmax>318</xmax>
		<ymax>291</ymax>
	</headbndbox>
	<bodybndbox>
		<xmin>70</xmin>
		<ymin>101</ymin>
		<xmax>432</xmax>
		<ymax>432</ymax>
	</bodybndbox>
</object>
</annotation>
