
<annotation>
	<folder>5355-n000126-golden_retriever</folder>
	<filename>n157708.jpeg</filename>
	<source>
		<database>THU-Dogs database</database>
	</source>
	<size>
		<width>374</width>
		<height>499</height>
		<depth>3</depth>
	</size>
	<segment>0</segment>
	<object>
	<name>golden_retriever</name>
	<pose>Unspecified</pose>
	<truncated>0</truncated>
	<difficult>0</difficult>
	<headbndbox>
		<xmin>76</xmin>
		<ymin>22</ymin>
		<xmax>281</xmax>
		<ymax>241</ymax>
	</headbndbox>
	<bodybndbox>
		<xmin>61</xmin>
		<ymin>19</ymin>
		<xmax>290</xmax>
		<ymax>499</ymax>
	</bodybndbox>
</object>
</annotation>
