
<annotation>
	<folder>5355-n000126-golden_retriever</folder>
	<filename>n157216.jpeg</filename>
	<source>
		<database>THU-Dogs database</database>
	</source>
	<size>
		<width>302</width>
		<height>403</height>
		<depth>3</depth>
	</size>
	<segment>0</segment>
	<object>
	<name>golden_retriever</name>
	<pose>Unspecified</pose>
	<truncated>0</truncated>
	<difficult>0</difficult>
	<headbndbox>
		<xmin>169</xmin>
		<ymin>177</ymin>
		<xmax>209</xmax>
		<ymax>213</ymax>
	</headbndbox>
	<bodybndbox>
		<xmin>108</xmin>
		<ymin>162</ymin>
		<xmax>216</xmax>
		<ymax>241</ymax>
	</bodybndbox>
</object>
</annotation>
