
<annotation>
	<folder>5355-n000126-golden_retriever</folder>
	<filename>n157518.jpg</filename>
	<source>
		<database>THU-Dogs database</database>
	</source>
	<size>
		<width>360</width>
		<height>509</height>
		<depth>3</depth>
	</size>
	<segment>0</segment>
	<object>
	<name>golden_retriever</name>
	<pose>Unspecified</pose>
	<truncated>0</truncated>
	<difficult>0</difficult>
	<headbndbox>
		<xmin>103</xmin>
		<ymin>106</ymin>
		<xmax>290</xmax>
		<ymax>289</ymax>
	</headbndbox>
	<bodybndbox>
		<xmin>75</xmin>
		<ymin>91</ymin>
		<xmax>337</xmax>
		<ymax>509</ymax>
	</bodybndbox>
</object>
</annotation>
