
<annotation>
	<folder>5355-n000126-golden_retriever</folder>
	<filename>n159243.jpeg</filename>
	<source>
		<database>THU-Dogs database</database>
	</source>
	<size>
		<width>314</width>
		<height>418</height>
		<depth>3</depth>
	</size>
	<segment>0</segment>
	<object>
	<name>golden_retriever</name>
	<pose>Unspecified</pose>
	<truncated>0</truncated>
	<difficult>0</difficult>
	<headbndbox>
		<xmin>119</xmin>
		<ymin>62</ymin>
		<xmax>217</xmax>
		<ymax>148</ymax>
	</headbndbox>
	<bodybndbox>
		<xmin>87</xmin>
		<ymin>51</ymin>
		<xmax>219</xmax>
		<ymax>250</ymax>
	</bodybndbox>
</object>
</annotation>
