
<annotation>
	<folder>5355-n000126-golden_retriever</folder>
	<filename>n159209.jpeg</filename>
	<source>
		<database>THU-Dogs database</database>
	</source>
	<size>
		<width>187</width>
		<height>406</height>
		<depth>3</depth>
	</size>
	<segment>0</segment>
	<object>
	<name>golden_retriever</name>
	<pose>Unspecified</pose>
	<truncated>0</truncated>
	<difficult>0</difficult>
	<headbndbox>
		<xmin>4</xmin>
		<ymin>39</ymin>
		<xmax>148</xmax>
		<ymax>177</ymax>
	</headbndbox>
	<bodybndbox>
		<xmin>0</xmin>
		<ymin>26</ymin>
		<xmax>187</xmax>
		<ymax>406</ymax>
	</bodybndbox>
</object>
</annotation>
