
<annotation>
	<folder>206-n000037-Scotch_terrier</folder>
	<filename>n112219.jpg</filename>
	<source>
		<database>THU-Dogs database</database>
	</source>
	<size>
		<width>225</width>
		<height>225</height>
		<depth>3</depth>
	</size>
	<segment>0</segment>
	<object>
	<name>Scotch_terrier</name>
	<pose>Unspecified</pose>
	<truncated>0</truncated>
	<difficult>0</difficult>
	<headbndbox>
		<xmin>17</xmin>
		<ymin>5</ymin>
		<xmax>101</xmax>
		<ymax>122</ymax>
	</headbndbox>
	<bodybndbox>
		<xmin>10</xmin>
		<ymin>5</ymin>
		<xmax>219</xmax>
		<ymax>192</ymax>
	</bodybndbox>
</object>
</annotation>
