
<annotation>
	<folder>227-n000070-groenendael</folder>
	<filename>n120470.jpg</filename>
	<source>
		<database>THU-Dogs database</database>
	</source>
	<size>
		<width>206</width>
		<height>245</height>
		<depth>3</depth>
	</size>
	<segment>0</segment>
	<object>
	<name>groenendael</name>
	<pose>Unspecified</pose>
	<truncated>0</truncated>
	<difficult>0</difficult>
	<headbndbox>
		<xmin>117</xmin>
		<ymin>50</ymin>
		<xmax>164</xmax>
		<ymax>116</ymax>
	</headbndbox>
	<bodybndbox>
		<xmin>17</xmin>
		<ymin>47</ymin>
		<xmax>173</xmax>
		<ymax>240</ymax>
	</bodybndbox>
</object>
</annotation>
