
<annotation>
	<folder>227-n000070-groenendael</folder>
	<filename>n120587.jpg</filename>
	<source>
		<database>THU-Dogs database</database>
	</source>
	<size>
		<width>500</width>
		<height>338</height>
		<depth>3</depth>
	</size>
	<segment>0</segment>
	<object>
	<name>groenendael</name>
	<pose>Unspecified</pose>
	<truncated>0</truncated>
	<difficult>0</difficult>
	<headbndbox>
		<xmin>328</xmin>
		<ymin>58</ymin>
		<xmax>435</xmax>
		<ymax>169</ymax>
	</headbndbox>
	<bodybndbox>
		<xmin>328</xmin>
		<ymin>58</ymin>
		<xmax>481</xmax>
		<ymax>334</ymax>
	</bodybndbox>
</object>
</annotation>
