
<annotation>
	<folder>228-n000085-Gordon_setter</folder>
	<filename>n123584.jpg</filename>
	<source>
		<database>THU-Dogs database</database>
	</source>
	<size>
		<width>500</width>
		<height>398</height>
		<depth>3</depth>
	</size>
	<segment>0</segment>
	<object>
	<name>Gordon_setter</name>
	<pose>Unspecified</pose>
	<truncated>0</truncated>
	<difficult>0</difficult>
	<headbndbox>
		<xmin>98</xmin>
		<ymin>111</ymin>
		<xmax>386</xmax>
		<ymax>348</ymax>
	</headbndbox>
	<bodybndbox>
		<xmin>98</xmin>
		<ymin>0</ymin>
		<xmax>464</xmax>
		<ymax>348</ymax>
	</bodybndbox>
</object>
</annotation>
